MANIFEST.in
README.rst
setup.py
setup_python_package/__init__.py
setup_python_package/__version__.py
setup_python_package/setup_python_package.py
setup_python_package.egg-info/PKG-INFO
setup_python_package.egg-info/SOURCES.txt
setup_python_package.egg-info/dependency_links.txt
setup_python_package.egg-info/entry_points.txt
setup_python_package.egg-info/requires.txt
setup_python_package.egg-info/top_level.txt
setup_python_package/badges/__init__.py
setup_python_package/badges/add_badge.py
setup_python_package/builders/__init__.py
setup_python_package/builders/build_gitignore.py
setup_python_package/builders/build_init.py
setup_python_package/builders/build_manifest.py
setup_python_package/builders/build_readme.py
setup_python_package/builders/build_setup.py
setup_python_package/builders/build_sonar.py
setup_python_package/builders/build_tests.py
setup_python_package/builders/build_travis.py
setup_python_package/builders/build_version.py
setup_python_package/builders/build_version_test.py
setup_python_package/builders/models/coveragerc
setup_python_package/builders/models/gitignore
setup_python_package/builders/models/readme
setup_python_package/builders/models/setup
setup_python_package/builders/models/sonar
setup_python_package/builders/models/travis
setup_python_package/builders/models/version
setup_python_package/builders/models/version_test
setup_python_package/enablers/__init__.py
setup_python_package/enablers/enable_codacy.py
setup_python_package/enablers/enable_codeclimate.py
setup_python_package/enablers/enable_coveralls.py
setup_python_package/enablers/enable_sonar.py
setup_python_package/enablers/enable_travis.py
setup_python_package/environment/__init__.py
setup_python_package/environment/is_cwd_a_repository.py
setup_python_package/environment/is_travis_installed.py
setup_python_package/queries/__init__.py
setup_python_package/queries/get_codacy_badge.py
setup_python_package/queries/get_codacy_code.py
setup_python_package/queries/get_code_climate_badges.py
setup_python_package/queries/get_code_climate_code.py
setup_python_package/queries/get_long_description.py
setup_python_package/queries/get_package_author_email.py
setup_python_package/queries/get_package_author_name.py
