Metadata-Version: 2.1
Name: setup-python-package
Version: 1.1.6
Summary: A python package that helps you create a python package.
Home-page: https://github.com/LucaCappelletti94/setup_python_package
Author: Luca Cappelletti
Author-email: cappelletti.luca94@gmail.com
License: MIT
Platform: UNKNOWN
Classifier: Development Status :: 3 - Alpha
Classifier: License :: OSI Approved :: MIT License
Classifier: Programming Language :: Python :: 3
Provides-Extra: test
